{
  "schema_version": 3,
  "plugin_type": "flag-node-generator",
  "plugins": [
    {
      "plugin_id": "CHANGE_ME_PLUGIN_ID",
      "plugin_type": "flag-node-generator",
      "version": "1.0",
      "description": "TODO",
      "requires": [],
      "produces": [
        {"artifact": "compose_path"},
        {"artifact": "flag"}
      ],
      "inputs": {
        "seed": {"type": "text", "required": true},
        "node_name": {"type": "text", "required": true},
        "flag_prefix": {"type": "text", "required": false}
      }
    }
  ],
  "implementations": [
    {
      "plugin_id": "CHANGE_ME_PLUGIN_ID",
      "name": "TODO",
      "language": "python",
      "source": {"type": "local-path", "path": "flag_node_generators/CHANGE_ME_FOLDER"},
      "compose": {"file": "docker-compose.yml", "service": "generator"},
      "description_hints": ["TODO"],
      "hint_templates": ["Next: ..."],
      "hint_template": "Next: ..."
    }
  ]
}
